Qt5HeOpencv4JisuanjiShijueXiangmuChuyiFix1/README.md
Qt5HeOpencv4JisuanjiShijueXiangmuChuyiFix1/__init__.py
Qt5HeOpencv4JisuanjiShijueXiangmuChuyiFix1/__main__.py
Qt5HeOpencv4JisuanjiShijueXiangmuChuyiFix1/file.epub
Qt5HeOpencv4JisuanjiShijueXiangmuChuyiFix1/index.html
Qt5HeOpencv4JisuanjiShijueXiangmuChuyiFix1/css/__init__.py
Qt5HeOpencv4JisuanjiShijueXiangmuChuyiFix1/css/annotations.css
Qt5HeOpencv4JisuanjiShijueXiangmuChuyiFix1/css/main.css
Qt5HeOpencv4JisuanjiShijueXiangmuChuyiFix1/css/normalize.css
Qt5HeOpencv4JisuanjiShijueXiangmuChuyiFix1/css/popup.css
Qt5HeOpencv4JisuanjiShijueXiangmuChuyiFix1/font/__init__.py
Qt5HeOpencv4JisuanjiShijueXiangmuChuyiFix1/font/fontello.eot
Qt5HeOpencv4JisuanjiShijueXiangmuChuyiFix1/font/fontello.svg
Qt5HeOpencv4JisuanjiShijueXiangmuChuyiFix1/font/fontello.ttf
Qt5HeOpencv4JisuanjiShijueXiangmuChuyiFix1/font/fontello.woff
Qt5HeOpencv4JisuanjiShijueXiangmuChuyiFix1/img/__init__.py
Qt5HeOpencv4JisuanjiShijueXiangmuChuyiFix1/img/annotator-glyph-sprite.png
Qt5HeOpencv4JisuanjiShijueXiangmuChuyiFix1/img/annotator-icon-sprite.png
Qt5HeOpencv4JisuanjiShijueXiangmuChuyiFix1/img/apple-touch-icon.png
Qt5HeOpencv4JisuanjiShijueXiangmuChuyiFix1/img/cancelfullscreen.png
Qt5HeOpencv4JisuanjiShijueXiangmuChuyiFix1/img/close.png
Qt5HeOpencv4JisuanjiShijueXiangmuChuyiFix1/img/fullscreen.png
Qt5HeOpencv4JisuanjiShijueXiangmuChuyiFix1/img/loader.gif
Qt5HeOpencv4JisuanjiShijueXiangmuChuyiFix1/img/menu-icon.png
Qt5HeOpencv4JisuanjiShijueXiangmuChuyiFix1/img/save.png
Qt5HeOpencv4JisuanjiShijueXiangmuChuyiFix1/img/saved.png
Qt5HeOpencv4JisuanjiShijueXiangmuChuyiFix1/img/settings-s.png
Qt5HeOpencv4JisuanjiShijueXiangmuChuyiFix1/img/settings.png
Qt5HeOpencv4JisuanjiShijueXiangmuChuyiFix1/img/star.png
Qt5HeOpencv4JisuanjiShijueXiangmuChuyiFix1/js/__init__.py
Qt5HeOpencv4JisuanjiShijueXiangmuChuyiFix1/js/epub.js
Qt5HeOpencv4JisuanjiShijueXiangmuChuyiFix1/js/epub.min.js
Qt5HeOpencv4JisuanjiShijueXiangmuChuyiFix1/js/epub.min.map
qt5_he_opencv4_jisuanji_shijue_xiangmu_chuyi_fix1-2025.3.25.1.dist-info/METADATA
qt5_he_opencv4_jisuanji_shijue_xiangmu_chuyi_fix1-2025.3.25.1.dist-info/WHEEL
qt5_he_opencv4_jisuanji_shijue_xiangmu_chuyi_fix1-2025.3.25.1.dist-info/entry_points.txt
qt5_he_opencv4_jisuanji_shijue_xiangmu_chuyi_fix1-2025.3.25.1.dist-info/top_level.txt
qt5_he_opencv4_jisuanji_shijue_xiangmu_chuyi_fix1-2025.3.25.1.dist-info/RECORD
